data_scientist_tools/DataScienceTools.py
data_scientist_tools/HappyDataScientist.py
data_scientist_tools/__init__.py
data_scientist_tools-1.5.dist-info/METADATA
data_scientist_tools-1.5.dist-info/WHEEL
data_scientist_tools-1.5.dist-info/top_level.txt
data_scientist_tools-1.5.dist-info/RECORD
